[
  {
    "id": "887402022",
    "price": "",
    "zipCode": "50076",
    "type": "SingleFamilyHome",
    "beds": "",
    "baths": "1.0",
    "squareFeet": "3706.0",
    "imageUrl": "https://dal6rfqhhpk45.cloudfront.net/3d24a678d4ceff84b8a8f69ba684c9aab68be750_md2.jpg"
  },
  {
    "id": "907371940",
    "price": "",
    "zipCode": "50076",
    "type": "SingleFamilyHome",
    "beds": "2.0",
    "baths": "2.0",
    "squareFeet": "1344.0",
    "imageUrl": "https://dal6rfqhhpk45.cloudfront.net/44d6bf321a4db313739c593bcf2d8ee853c71f32_md2.jpg"
  },
  {
    "id": "897984021",
    "price": "",
    "zipCode": "50076",
    "type": "VacantLand",
    "beds": "",
    "baths": "",
    "squareFeet": "",
    "imageUrl": "https://dal6rfqhhpk45.cloudfront.net/3cfd462cbb586ccf78509a85a8fc1b634f198e9d_md2.jpg"
  },
  {
    "id": "915676937",
    "price": "",
    "zipCode": "50076",
    "type": "SingleFamilyHome",
    "beds": "2.0",
    "baths": "1.0",
    "squareFeet": "1066.0",
    "imageUrl": "https://dal6rfqhhpk45.cloudfront.net/fc34fd1a6d62ca5d672425801110d98050938b28_md2.jpg"
  },
  {
    "id": "907222318",
    "price": "",
    "zipCode": "50076",
    "type": "SingleFamilyHome",
    "beds": "3.0",
    "baths": "1.0",
    "squareFeet": "1824.0",
    "imageUrl": "https://dal6rfqhhpk45.cloudfront.net/6fc97ce45f57556d4682d6b0635c96d201536182_md2.jpg"
  },
  {
    "id": "917913538",
    "price": "",
    "zipCode": "50022",
    "type": "SingleFamilyHome",
    "beds": "3.0",
    "baths": "2.0",
    "squareFeet": "1996.0",
    "imageUrl": "https://dal6rfqhhpk45.cloudfront.net/002d06f2b213d852b22363fa624ab26c612ee69f_md2.jpg"
  },
  {
    "id": "919407068",
    "price": "",
    "zipCode": "50022",
    "type": "SingleFamilyHome",
    "beds": "3.0",
    "baths": "2.0",
    "squareFeet": "1466.0",
    "imageUrl": "https://dal6rfqhhpk45.cloudfront.net/3d3bf5db571bb1d8d8855702dfd3392addc9b2ae_md2.jpg"
  },
  {
    "id": "808786643",
    "price": "",
    "zipCode": "50022",
    "type": "SingleFamilyHome",
    "beds": "6.0",
    "baths": "4.0",
    "squareFeet": "2127.0",
    "imageUrl": "https://dal6rfqhhpk45.cloudfront.net/5844a1eeca1ce4e1a2ba2c0eded747e3c53eeab9_md2.jpg"
  },
  {
    "id": "891692479",
    "price": "",
    "zipCode": "50076",
    "type": "SingleFamilyHome",
    "beds": "3.0",
    "baths": "2.0",
    "squareFeet": "2238.0",
    "imageUrl": "https://dal6rfqhhpk45.cloudfront.net/2f16ab9f907226717b58da1e6e0c7964626c232e_md2.jpg"
  },
  {
    "id": "918831868",
    "price": "",
    "zipCode": "51531",
    "type": "SingleFamilyHome",
    "beds": "2.0",
    "baths": "2.0",
    "squareFeet": "890.0",
    "imageUrl": "https://dal6rfqhhpk45.cloudfront.net/9a7fdfa07b9f9a8008a4fc5a3d62cd289f4488da_md2.jpg"
  },
  {
    "id": "911052341",
    "price": "",
    "zipCode": "51531",
    "type": "SingleFamilyHome",
    "beds": "4.0",
    "baths": "2.0",
    "squareFeet": "1678.0",
    "imageUrl": "https://dal6rfqhhpk45.cloudfront.net/74b2a483a52c0fc90d73c98d7ba5b900ffc553e9_md2.jpg"
  },
  {
    "id": "916561549",
    "price": "",
    "zipCode": "51531",
    "type": "SingleFamilyHome",
    "beds": "2.0",
    "baths": "2.0",
    "squareFeet": "1560.0",
    "imageUrl": "https://dal6rfqhhpk45.cloudfront.net/8a1cb57615889c4d493ea0baa60180bb01389b6f_md2.jpg"
  },
  {
    "id": "917685226",
    "price": "",
    "zipCode": "51531",
    "type": "SingleFamilyHome",
    "beds": "5.0",
    "baths": "1.0",
    "squareFeet": "2224.0",
    "imageUrl": "https://dal6rfqhhpk45.cloudfront.net/9aed4d4e5a5aa234f55a0725ec34653e6c379194_md2.jpg"
  },
  {
    "id": "903907747",
    "price": "",
    "zipCode": "50020",
    "type": "SingleFamilyHome",
    "beds": "2.0",
    "baths": "1.0",
    "squareFeet": "905.0",
    "imageUrl": "https://dal6rfqhhpk45.cloudfront.net/0740a542c7e062411a8d9b1be8c75742f44b4c5d_md2.jpg"
  },
  {
    "id": "891097169",
    "price": "",
    "zipCode": "50020",
    "type": "SingleFamilyHome",
    "beds": "3.0",
    "baths": "1.0",
    "squareFeet": "1620.0",
    "imageUrl": "https://dal6rfqhhpk45.cloudfront.net/386b6d5de20ec6d7c00ae0423bc942c0dbe940bb_md2.jpg"
  },
  {
    "id": "912154819",
    "price": "",
    "zipCode": "50020",
    "type": "SingleFamilyHome",
    "beds": "4.0",
    "baths": "3.0",
    "squareFeet": "2982.0",
    "imageUrl": "https://dal6rfqhhpk45.cloudfront.net/0c767b0514643e5ebd2d41e07ba85f8c67a6a5b0_md2.jpg"
  },
  {
    "id": "892812521",
    "price": "",
    "zipCode": "50020",
    "type": "SingleFamilyHome",
    "beds": "3.0",
    "baths": "1.0",
    "squareFeet": "1244.0",
    "imageUrl": "https://dal6rfqhhpk45.cloudfront.net/8abe9af9a147ae2c3aa0c79812cd63fef75a5992_md2.jpg"
  },
  {
    "id": "884162806",
    "price": "",
    "zipCode": "50022",
    "type": "SingleFamilyHome",
    "beds": "3.0",
    "baths": "1.0",
    "squareFeet": "1866.0",
    "imageUrl": "https://dal6rfqhhpk45.cloudfront.net/fc842596423c1a5016f9daf68f1479bad02d575d_md2.jpg"
  },
  {
    "id": "911536741",
    "price": "",
    "zipCode": "50022",
    "type": "SingleFamilyHome",
    "beds": "4.0",
    "baths": "2.0",
    "squareFeet": "2424.0",
    "imageUrl": "https://dal6rfqhhpk45.cloudfront.net/c9bd7489297aead7fe105632c175e5b4c1f23f19_md2.jpg"
  },
  {
    "id": "885183524",
    "price": "",
    "zipCode": "50022",
    "type": "SingleFamilyHome",
    "beds": "",
    "baths": "3.0",
    "squareFeet": "2449.0",
    "imageUrl": "https://dal6rfqhhpk45.cloudfront.net/6abd2bd312a3f6e95465afade37feed0a91f512f_md2.jpg"
  },
  {
    "id": "877701913",
    "price": "",
    "zipCode": "50022",
    "type": "TownhouseorCondo",
    "beds": "3.0",
    "baths": "3.0",
    "squareFeet": "1837.0",
    "imageUrl": "https://dal6rfqhhpk45.cloudfront.net/d33f819bf8621a7d5279882d27a5e72f6a36529b_md2.jpg"
  },
  {
    "id": "920671754",
    "price": "",
    "zipCode": "50022",
    "type": "SingleFamilyHome",
    "beds": "2.0",
    "baths": "2.0",
    "squareFeet": "1660.0",
    "imageUrl": "https://dal6rfqhhpk45.cloudfront.net/4e71e19e309db52869353e9f20e3c56698812f0f_md2.jpg"
  },
  {
    "id": "903336907",
    "price": "",
    "zipCode": "50022",
    "type": "TownhouseorCondo",
    "beds": "2.0",
    "baths": "2.0",
    "squareFeet": "1267.0",
    "imageUrl": "https://dal6rfqhhpk45.cloudfront.net/38a9150c3d173a1d26a158b3bb43193ee7c97eef_md2.jpg"
  },
  {
    "id": "918171955",
    "price": "",
    "zipCode": "50022",
    "type": "SingleFamilyHome",
    "beds": "3.0",
    "baths": "2.0",
    "squareFeet": "1591.0",
    "imageUrl": "https://dal6rfqhhpk45.cloudfront.net/21a8fe15ee25f9678b2f6a3b050f8c3ab64c2ba2_md2.jpg"
  },
  {
    "id": "917647698",
    "price": "",
    "zipCode": "50022",
    "type": "VacantLand",
    "beds": "",
    "baths": "",
    "squareFeet": "",
    "imageUrl": "https://dal6rfqhhpk45.cloudfront.net/4eb977f3fce9539bed2d66b338640717828a696f_md2.jpg"
  },
  {
    "id": "916849019",
    "price": "",
    "zipCode": "50022",
    "type": "SingleFamilyHome",
    "beds": "",
    "baths": "",
    "squareFeet": "",
    "imageUrl": "https://dal6rfqhhpk45.cloudfront.net/ed48c02bd70e1cf3872eb767e08412770d4114f6_md2.jpg"
  },
  {
    "id": "903687418",
    "price": "",
    "zipCode": "50022",
    "type": "SingleFamilyHome",
    "beds": "2.0",
    "baths": "1.0",
    "squareFeet": "1440.0",
    "imageUrl": "https://dal6rfqhhpk45.cloudfront.net/5c7ae3883b7991d181f771dd0a9010bc2d3bc4e5_md2.jpg"
  },
  {
    "id": "825755721",
    "price": "",
    "zipCode": "50022",
    "type": "VacantLand",
    "beds": "",
    "baths": "",
    "squareFeet": "",
    "imageUrl": "https://dal6rfqhhpk45.cloudfront.net/07c45eb2d865f9221bd04c6fe60fa0aa8cb3612b_md2.jpg"
  },
  {
    "id": "825755123",
    "price": "",
    "zipCode": "50022",
    "type": "VacantLand",
    "beds": "",
    "baths": "",
    "squareFeet": "",
    "imageUrl": "https://dal6rfqhhpk45.cloudfront.net/f1d357ad7ef638f25175153f71eadf42e43fea0e_md2.jpg"
  },
  {
    "id": "825754188",
    "price": "",
    "zipCode": "50022",
    "type": "VacantLand",
    "beds": "",
    "baths": "",
    "squareFeet": "",
    "imageUrl": "https://dal6rfqhhpk45.cloudfront.net/ef4fb05f4917b9c2d678fb13f1beb6443cbd599c_md2.jpg"
  },
  {
    "id": "792053504",
    "price": "",
    "zipCode": "50022",
    "type": "VacantLand",
    "beds": "",
    "baths": "",
    "squareFeet": "",
    "imageUrl": "https://dal6rfqhhpk45.cloudfront.net/b259ba2a4f056871891fc6a4e8d99441632d82db_md2.jpg"
  },
  {
    "id": "898683492",
    "price": "",
    "zipCode": "50022",
    "type": "SingleFamilyHome",
    "beds": "4.0",
    "baths": "3.0",
    "squareFeet": "2156.0",
    "imageUrl": "https://dal6rfqhhpk45.cloudfront.net/5d7ea10295f70d417b3ba4679e1eb1a1720b73df_md2.jpg"
  },
  {
    "id": "885192327",
    "price": "",
    "zipCode": "50022",
    "type": "VacantLand",
    "beds": "",
    "baths": "",
    "squareFeet": "",
    "imageUrl": "https://dal6rfqhhpk45.cloudfront.net/57925d1f39096f0c987af1996429c498ba17a3c6_md2.jpg"
  },
  {
    "id": "895725686",
    "price": "",
    "zipCode": "50022",
    "type": "TownhouseorCondo",
    "beds": "2.0",
    "baths": "2.0",
    "squareFeet": "1356.0",
    "imageUrl": "https://dal6rfqhhpk45.cloudfront.net/535a73232ae66a0d9035684fa7b4dce39aa3222b_md2.jpg"
  },
  {
    "id": "856276191",
    "price": "",
    "zipCode": "50022",
    "type": "SingleFamilyHome",
    "beds": "3.0",
    "baths": "2.0",
    "squareFeet": "1224.0",
    "imageUrl": "https://dal6rfqhhpk45.cloudfront.net/7eef20226e27229828d5e294c384c5c2a26e89cb_md2.jpg"
  },
  {
    "id": "842131919",
    "price": "",
    "zipCode": "50022",
    "type": "SingleFamilyHome",
    "beds": "3.0",
    "baths": "1.0",
    "squareFeet": "930.0",
    "imageUrl": "https://dal6rfqhhpk45.cloudfront.net/a0c9bf204477f1c2d80d3ef94c40bcc9b19f51e0_md2.jpg"
  },
  {
    "id": "875983455",
    "price": "",
    "zipCode": "50022",
    "type": "SingleFamilyHome",
    "beds": "3.0",
    "baths": "1.0",
    "squareFeet": "923.0",
    "imageUrl": "https://dal6rfqhhpk45.cloudfront.net/85d3882a0e09ef34f0a259b21b6dab3c1218ac41_md2.jpg"
  },
  {
    "id": "869040548",
    "price": "",
    "zipCode": "50022",
    "type": "TownhouseorCondo",
    "beds": "2.0",
    "baths": "2.0",
    "squareFeet": "2300.0",
    "imageUrl": "https://dal6rfqhhpk45.cloudfront.net/d04b11b1890f61c4a00ba859e5e914c915a79b24_md2.jpg"
  },
  {
    "id": "807962639",
    "price": "",
    "zipCode": "50022",
    "type": "SingleFamilyHome",
    "beds": "3.0",
    "baths": "1.0",
    "squareFeet": "1256.0",
    "imageUrl": "https://dal6rfqhhpk45.cloudfront.net/d5fd4a5ac2cd168cfbe89af6be193333c66ebda0_md2.jpg"
  },
  {
    "id": "910438897",
    "price": "",
    "zipCode": "50022",
    "type": "SingleFamilyHome",
    "beds": "3.0",
    "baths": "1.0",
    "squareFeet": "1236.0",
    "imageUrl": "https://dal6rfqhhpk45.cloudfront.net/0331e1e8215acddba734c67da6d89729e8c97c60_md2.jpg"
  },
  {
    "id": "880138689",
    "price": "",
    "zipCode": "50022",
    "type": "SingleFamilyHome",
    "beds": "5.0",
    "baths": "1.0",
    "squareFeet": "3139.0",
    "imageUrl": "https://dal6rfqhhpk45.cloudfront.net/b2d4d945cf1cd76edf2ff7c3f23475af0261b686_md2.jpg"
  },
  {
    "id": "865532747",
    "price": "",
    "zipCode": "50022",
    "type": "SingleFamilyHome",
    "beds": "3.0",
    "baths": "2.0",
    "squareFeet": "1600.0",
    "imageUrl": "https://dal6rfqhhpk45.cloudfront.net/9b64039ab5cdaf07a582028e39df763190bc3c42_md2.jpg"
  },
  {
    "id": "907036113",
    "price": "",
    "zipCode": "50022",
    "type": "SingleFamilyHome",
    "beds": "2.0",
    "baths": "2.0",
    "squareFeet": "1015.0",
    "imageUrl": "https://dal6rfqhhpk45.cloudfront.net/7d7e1ae17c615b4fa55536fc5205b8b93257ef9d_md2.jpg"
  },
  {
    "id": "796484742",
    "price": "",
    "zipCode": "50022",
    "type": "SingleFamilyHome",
    "beds": "3.0",
    "baths": "1.0",
    "squareFeet": "966.0",
    "imageUrl": "https://dal6rfqhhpk45.cloudfront.net/38748fadb2de60085ef00399a7e542ad319491a9_md2.jpg"
  },
  {
    "id": "852987606",
    "price": "",
    "zipCode": "51543",
    "type": "SingleFamilyHome",
    "beds": "",
    "baths": "3.0",
    "squareFeet": "1792.0",
    "imageUrl": "https://dal6rfqhhpk45.cloudfront.net/c69f0a2964edd1703b84c6dc8850744b9f120c21_md2.jpg"
  },
  {
    "id": "907037128",
    "price": "",
    "zipCode": "50022",
    "type": "TownhouseorCondo",
    "beds": "2.0",
    "baths": "1.0",
    "squareFeet": "963.0",
    "imageUrl": "https://dal6rfqhhpk45.cloudfront.net/804925e5704edd3a60c5a0ce20494039aa252c69_md2.jpg"
  },
  {
    "id": "918517741",
    "price": "",
    "zipCode": "50022",
    "type": "SingleFamilyHome",
    "beds": "2.0",
    "baths": "2.0",
    "squareFeet": "1290.0",
    "imageUrl": "https://dal6rfqhhpk45.cloudfront.net/bad5543f2341398d174570a63533e1d0fd55f937_md2.jpg"
  },
  {
    "id": "858150406",
    "price": "",
    "zipCode": "50022",
    "type": "SingleFamilyHome",
    "beds": "4.0",
    "baths": "5.0",
    "squareFeet": "3489.0",
    "imageUrl": "https://dal6rfqhhpk45.cloudfront.net/b3f450b2e16fbd3e8ece9972b017714c0ab7af25_md2.jpg"
  },
  {
    "id": "799884854",
    "price": "",
    "zipCode": "50022",
    "type": "SingleFamilyHome",
    "beds": "3.0",
    "baths": "2.0",
    "squareFeet": "1289.0",
    "imageUrl": "https://dal6rfqhhpk45.cloudfront.net/ffd9ad8b1f52df98fc4891daf9b224841d09267f_md2.jpg"
  },
  {
    "id": "894723275",
    "price": "",
    "zipCode": "50022",
    "type": "SingleFamilyHome",
    "beds": "3.0",
    "baths": "2.0",
    "squareFeet": "1285.0",
    "imageUrl": "https://dal6rfqhhpk45.cloudfront.net/bd01ce0e5ab879ab00cd2bad3f58be02b9c1d348_md2.jpg"
  },
  {
    "id": "864986789",
    "price": "",
    "zipCode": "50022",
    "type": "SingleFamilyHome",
    "beds": "3.0",
    "baths": "2.0",
    "squareFeet": "1075.0",
    "imageUrl": "https://dal6rfqhhpk45.cloudfront.net/1272103ec07b9b2a0e6fbc5ce27243c56789c74a_md2.jpg"
  },
  {
    "id": "920748428",
    "price": "",
    "zipCode": "50022",
    "type": "SingleFamilyHome",
    "beds": "3.0",
    "baths": "2.0",
    "squareFeet": "1263.0",
    "imageUrl": "https://dal6rfqhhpk45.cloudfront.net/20bb66e17d0a8fad93b1718e6a1703a20f300613_md2.jpg"
  },
  {
    "id": "792055901",
    "price": "",
    "zipCode": "50022",
    "type": "VacantLand",
    "beds": "",
    "baths": "",
    "squareFeet": "",
    "imageUrl": "https://dal6rfqhhpk45.cloudfront.net/637020f244244c08464cc919057a0f86ef66c8de_md2.jpg"
  },
  {
    "id": "906868375",
    "price": "",
    "zipCode": "50022",
    "type": "SingleFamilyHome",
    "beds": "3.0",
    "baths": "1.0",
    "squareFeet": "1621.0",
    "imageUrl": "https://dal6rfqhhpk45.cloudfront.net/db142bfd3975966c19f3c5ca4b5e706459696f18_md2.jpg"
  },
  {
    "id": "899676336",
    "price": "",
    "zipCode": "50022",
    "type": "SingleFamilyHome",
    "beds": "2.0",
    "baths": "2.0",
    "squareFeet": "962.0",
    "imageUrl": "https://dal6rfqhhpk45.cloudfront.net/9304a842b1f55c996f40905cb59d0b97d2733f3c_md2.jpg"
  },
  {
    "id": "827795241",
    "price": "",
    "zipCode": "50022",
    "type": "VacantLand",
    "beds": "",
    "baths": "",
    "squareFeet": "",
    "imageUrl": "https://dal6rfqhhpk45.cloudfront.net/7ba2f0423559a84ee6e1fbaca4866c0fb66cbc7e_md2.jpg"
  },
  {
    "id": "905881911",
    "price": "",
    "zipCode": "50022",
    "type": "SingleFamilyHome",
    "beds": "5.0",
    "baths": "2.0",
    "squareFeet": "1990.0",
    "imageUrl": "https://dal6rfqhhpk45.cloudfront.net/eaec5a645d582252ad9da5cf063f88851dec3104_md2.jpg"
  },
  {
    "id": "903384651",
    "price": "",
    "zipCode": "50022",
    "type": "SingleFamilyHome",
    "beds": "2.0",
    "baths": "2.0",
    "squareFeet": "1467.0",
    "imageUrl": "https://dal6rfqhhpk45.cloudfront.net/c6bb42a309544ce26facb95d9272ea828f10a60a_md2.jpg"
  },
  {
    "id": "888119373",
    "price": "",
    "zipCode": "50022",
    "type": "SingleFamilyHome",
    "beds": "4.0",
    "baths": "3.0",
    "squareFeet": "2116.0",
    "imageUrl": "https://dal6rfqhhpk45.cloudfront.net/2d4c234b7d42b018be7d1823894296b1ec354d9f_md2.jpg"
  },
  {
    "id": "914680799",
    "price": "",
    "zipCode": "50022",
    "type": "SingleFamilyHome",
    "beds": "3.0",
    "baths": "1.0",
    "squareFeet": "1199.0",
    "imageUrl": "https://dal6rfqhhpk45.cloudfront.net/47eddf1bdf0e5ffdff72b6d435cce1db5ead3a92_md2.jpg"
  },
  {
    "id": "883679441",
    "price": "",
    "zipCode": "50022",
    "type": "TownhouseorCondo",
    "beds": "2.0",
    "baths": "1.0",
    "squareFeet": "882.0",
    "imageUrl": "https://dal6rfqhhpk45.cloudfront.net/cd0d63692e841ccb255033b1d05b92807a0af69f_md2.jpg"
  },
  {
    "id": "907200747",
    "price": "",
    "zipCode": "50022",
    "type": "SingleFamilyHome",
    "beds": "3.0",
    "baths": "3.0",
    "squareFeet": "1124.0",
    "imageUrl": "https://dal6rfqhhpk45.cloudfront.net/08ff0a46314e16425cda8e1d1333d3b3c2026282_md2.jpg"
  },
  {
    "id": "887025173",
    "price": "",
    "zipCode": "50022",
    "type": "SingleFamilyHome",
    "beds": "4.0",
    "baths": "3.0",
    "squareFeet": "2543.0",
    "imageUrl": "https://dal6rfqhhpk45.cloudfront.net/e0aede66f8704200e3559e3121a98a25cbf0a0f5_md2.jpg"
  },
  {
    "id": "905914794",
    "price": "",
    "zipCode": "50022",
    "type": "SingleFamilyHome",
    "beds": "4.0",
    "baths": "2.0",
    "squareFeet": "2157.0",
    "imageUrl": "https://dal6rfqhhpk45.cloudfront.net/b2764423da964e8e0e73f3c238b5803a70080566_md2.jpg"
  },
  {
    "id": "841941766",
    "price": "",
    "zipCode": "50022",
    "type": "SingleFamilyHome",
    "beds": "3.0",
    "baths": "1.0",
    "squareFeet": "1429.0",
    "imageUrl": "https://dal6rfqhhpk45.cloudfront.net/14ba9b72a2534e129c3c2b33ebd4db7ad7e49b96_md2.jpg"
  },
  {
    "id": "903964928",
    "price": "",
    "zipCode": "50025",
    "type": "SingleFamilyHome",
    "beds": "",
    "baths": "",
    "squareFeet": "",
    "imageUrl": "https://dal6rfqhhpk45.cloudfront.net/3b6930347d074f242f0751338dacd332aca7b86b_md2.jpg"
  },
  {
    "id": "910861357",
    "price": "",
    "zipCode": "50022",
    "type": "SingleFamilyHome",
    "beds": "3.0",
    "baths": "4.0",
    "squareFeet": "2850.0",
    "imageUrl": "https://dal6rfqhhpk45.cloudfront.net/0bd3deea39247602cc7b108cd3b71225b53010fa_md2.jpg"
  },
  {
    "id": "908167651",
    "price": "",
    "zipCode": "50022",
    "type": "SingleFamilyHome",
    "beds": "4.0",
    "baths": "2.0",
    "squareFeet": "2250.0",
    "imageUrl": "https://dal6rfqhhpk45.cloudfront.net/59bcc7161bc86ea52092a59aeffd1f336758fe85_md2.jpg"
  },
  {
    "id": "911944395",
    "price": "",
    "zipCode": "50022",
    "type": "SingleFamilyHome",
    "beds": "4.0",
    "baths": "3.0",
    "squareFeet": "2407.0",
    "imageUrl": "https://dal6rfqhhpk45.cloudfront.net/dad6b7f7a277158ce6cb2be4b795361e6b4492b0_md2.jpg"
  },
  {
    "id": "873068079",
    "price": "",
    "zipCode": "50022",
    "type": "SingleFamilyHome",
    "beds": "2.0",
    "baths": "2.0",
    "squareFeet": "1752.0",
    "imageUrl": "https://dal6rfqhhpk45.cloudfront.net/e6d019d8853b5d182e4543c1068eb1b058cfb3b0_md2.jpg"
  },
  {
    "id": "799521985",
    "price": "",
    "zipCode": "50022",
    "type": "SingleFamilyHome",
    "beds": "4.0",
    "baths": "2.0",
    "squareFeet": "1078.0",
    "imageUrl": "https://dal6rfqhhpk45.cloudfront.net/61391076cfbe35026e632b9fbe4c0176c9cc2232_md2.jpg"
  },
  {
    "id": "916485798",
    "price": "",
    "zipCode": "50022",
    "type": "SingleFamilyHome",
    "beds": "3.0",
    "baths": "2.0",
    "squareFeet": "1517.0",
    "imageUrl": "https://dal6rfqhhpk45.cloudfront.net/05892034973b4260533725fad799c9652a47c4fb_md2.jpg"
  },
  {
    "id": "842005576",
    "price": "",
    "zipCode": "50022",
    "type": "SingleFamilyHome",
    "beds": "3.0",
    "baths": "1.0",
    "squareFeet": "1655.0",
    "imageUrl": "https://dal6rfqhhpk45.cloudfront.net/adaa5c2dc69c64ac5b5f36ddcc21ce71ed327971_md2.jpg"
  },
  {
    "id": "906096142",
    "price": "",
    "zipCode": "50022",
    "type": "TownhouseorCondo",
    "beds": "2.0",
    "baths": "2.0",
    "squareFeet": "1440.0",
    "imageUrl": "https://dal6rfqhhpk45.cloudfront.net/a59fb576d17b39795b724db04723f0bb373eff3d_md2.jpg"
  },
  {
    "id": "907251028",
    "price": "",
    "zipCode": "50022",
    "type": "SingleFamilyHome",
    "beds": "3.0",
    "baths": "3.0",
    "squareFeet": "1702.0",
    "imageUrl": "https://dal6rfqhhpk45.cloudfront.net/4b77e1c397a69e32f166d767f3004483fc18f26a_md2.jpg"
  },
  {
    "id": "822172477",
    "price": "",
    "zipCode": "51543",
    "type": "SingleFamilyHome",
    "beds": "4.0",
    "baths": "2.0",
    "squareFeet": "1402.0",
    "imageUrl": "https://dal6rfqhhpk45.cloudfront.net/8779a9944ebbc458587fe8ca4f5ea16f82862d5e_md2.jpg"
  },
  {
    "id": "886935023",
    "price": "",
    "zipCode": "50025",
    "type": "SingleFamilyHome",
    "beds": "3.0",
    "baths": "2.0",
    "squareFeet": "1020.0",
    "imageUrl": "https://dal6rfqhhpk45.cloudfront.net/c11ef4a526042772e22d5f99d9a28406ce3ecd3f_md2.jpg"
  },
  {
    "id": "920258530",
    "price": "",
    "zipCode": "50022",
    "type": "SingleFamilyHome",
    "beds": "3.0",
    "baths": "2.0",
    "squareFeet": "1890.0",
    "imageUrl": "https://dal6rfqhhpk45.cloudfront.net/31986b232fb2922e67608a9fe5bbb7a1ccf4281d_md2.jpg"
  },
  {
    "id": "878609602",
    "price": "",
    "zipCode": "50022",
    "type": "SingleFamilyHome",
    "beds": "3.0",
    "baths": "4.0",
    "squareFeet": "3031.0",
    "imageUrl": "https://dal6rfqhhpk45.cloudfront.net/1afe70b8a84ef19a6bc0e3634cb8ac2aa292ebab_md2.jpg"
  },
  {
    "id": "898112587",
    "price": "",
    "zipCode": "51552",
    "type": "MobileorManufacturedHome",
    "beds": "2.0",
    "baths": "1.0",
    "squareFeet": "938.0",
    "imageUrl": "https://dal6rfqhhpk45.cloudfront.net/c49eb7dbf665ba31aaef9a2966f2c7bd27c71325_md2.jpg"
  },
  {
    "id": "898174625",
    "price": "",
    "zipCode": "51531",
    "type": "SingleFamilyHome",
    "beds": "4.0",
    "baths": "2.0",
    "squareFeet": "2404.0",
    "imageUrl": "https://dal6rfqhhpk45.cloudfront.net/6dd7a431e6df78ec4548e4bd637a91404006979e_md2.jpg"
  },
  {
    "id": "913287821",
    "price": "",
    "zipCode": "50025",
    "type": "SingleFamilyHome",
    "beds": "3.0",
    "baths": "3.0",
    "squareFeet": "2053.0",
    "imageUrl": "https://dal6rfqhhpk45.cloudfront.net/1808631ed8acb674bce96d8ec1040c0f609fa281_md2.jpg"
  }
]