[
  {
    "id": "890185542",
    "price": "",
    "zipCode": "98002",
    "type": "SingleFamilyHome",
    "beds": "",
    "baths": "1.0",
    "squareFeet": "192.0",
    "imageUrl": "https://dal6rfqhhpk45.cloudfront.net/4853e11f61a780c9458a09d69b2b7f0ad7d151e4_md2.jpg"
  },
  {
    "id": "894721713",
    "price": "",
    "zipCode": "98092",
    "type": "SingleFamilyHome",
    "beds": "3.0",
    "baths": "2.0",
    "squareFeet": "1390.0",
    "imageUrl": "https://dal6rfqhhpk45.cloudfront.net/009402186d63bf01060823305df5d4a6369cbf81_md2.jpg"
  },
  {
    "id": "906102480",
    "price": "",
    "zipCode": "98002",
    "type": "SingleFamilyHome",
    "beds": "3.0",
    "baths": "",
    "squareFeet": "2410.0",
    "imageUrl": "https://dal6rfqhhpk45.cloudfront.net/3cd140ec2ef4d8fbedf9aa4fe74f62da54cfca9d_md2.jpg"
  },
  {
    "id": "890157815",
    "price": "",
    "zipCode": "98092",
    "type": "SingleFamilyHome",
    "beds": "4.0",
    "baths": "4.0",
    "squareFeet": "4245.0",
    "imageUrl": "https://dal6rfqhhpk45.cloudfront.net/8fa4487e7039c03b8a94647122ff50f719a02e45_md2.jpg"
  },
  {
    "id": "890653356",
    "price": "",
    "zipCode": "98092",
    "type": "MobileOrManufacturedHome",
    "beds": "3.0",
    "baths": "2.0",
    "squareFeet": "1680.0",
    "imageUrl": "https://dal6rfqhhpk45.cloudfront.net/230c0a942aa7a16bb38d79e2a187216b1fb6af72_md2.jpg"
  },
  {
    "id": "911348208",
    "price": "",
    "zipCode": "98001",
    "type": "SingleFamilyHome",
    "beds": "4.0",
    "baths": "2.0",
    "squareFeet": "2537.0",
    "imageUrl": "https://dal6rfqhhpk45.cloudfront.net/88ed77c48d9eb80fb200ff5a78f796b33f1fe7f4_md2.jpg"
  },
  {
    "id": "900507057",
    "price": "",
    "zipCode": "98001",
    "type": "SingleFamilyHome",
    "beds": "2.0",
    "baths": "1.0",
    "squareFeet": "900.0",
    "imageUrl": "https://dal6rfqhhpk45.cloudfront.net/e023797580c276fb9d414c2bc66a86f1b3118c6c_md2.jpg"
  },
  {
    "id": "890892067",
    "price": "",
    "zipCode": "98092",
    "type": "SingleFamilyHome",
    "beds": "5.0",
    "baths": "",
    "squareFeet": "2480.0",
    "imageUrl": "https://dal6rfqhhpk45.cloudfront.net/2ba79b883ed448304b21e4486ee74097ab93d2a5_md2.jpg"
  },
  {
    "id": "890673105",
    "price": "",
    "zipCode": "98047",
    "type": "SingleFamilyHome",
    "beds": "4.0",
    "baths": "2.0",
    "squareFeet": "1820.0",
    "imageUrl": "https://dal6rfqhhpk45.cloudfront.net/771353e9643eadb2794bf9324ed5995f7393f687_md2.jpg"
  },
  {
    "id": "890920262",
    "price": "",
    "zipCode": "98092",
    "type": "SingleFamilyHome",
    "beds": "3.0",
    "baths": "2.0",
    "squareFeet": "2100.0",
    "imageUrl": "https://dal6rfqhhpk45.cloudfront.net/601ea315093b41c989b3f8e7e98b29bb986cea2c_md2.jpg"
  },
  {
    "id": "890307511",
    "price": "",
    "zipCode": "98002",
    "type": "SingleFamilyHome",
    "beds": "3.0",
    "baths": "2.0",
    "squareFeet": "2437.0",
    "imageUrl": "https://dal6rfqhhpk45.cloudfront.net/305ad8945b55e5c8e2f5e52adf31d876b67e925a_md2.jpg"
  },
  {
    "id": "890271845",
    "price": "",
    "zipCode": "98002",
    "type": "SingleFamilyHome",
    "beds": "4.0",
    "baths": "2.0",
    "squareFeet": "2480.0",
    "imageUrl": "https://dal6rfqhhpk45.cloudfront.net/afbc8bacd1182210f3444565d79207959308daa1_md2.jpg"
  },
  {
    "id": "890981930",
    "price": "",
    "zipCode": "98092",
    "type": "SingleFamilyHome",
    "beds": "5.0",
    "baths": "2.0",
    "squareFeet": "3239.0",
    "imageUrl": "https://dal6rfqhhpk45.cloudfront.net/e0b3523c272d8daa96851f11beb0c380cf70e836_md2.jpg"
  },
  {
    "id": "890729387",
    "price": "",
    "zipCode": "98092",
    "type": "SingleFamilyHome",
    "beds": "3.0",
    "baths": "1.0",
    "squareFeet": "1520.0",
    "imageUrl": "https://dal6rfqhhpk45.cloudfront.net/312b4e4cff50c1cef4b85d3fc92ef92970bb533d_md2.jpg"
  },
  {
    "id": "890998131",
    "price": "",
    "zipCode": "98092",
    "type": "SingleFamilyHome",
    "beds": "3.0",
    "baths": "2.0",
    "squareFeet": "1675.0",
    "imageUrl": "https://dal6rfqhhpk45.cloudfront.net/3b14ca5b1ec19b18013e216c16b96cbb64aa3bec_md2.jpg"
  },
  {
    "id": "890855348",
    "price": "",
    "zipCode": "98001",
    "type": "SingleFamilyHome",
    "beds": "3.0",
    "baths": "2.0",
    "squareFeet": "1710.0",
    "imageUrl": "https://dal6rfqhhpk45.cloudfront.net/cd5a13ac81743fbdb9cd12f1cf14d8a516945bf5_md2.jpg"
  },
  {
    "id": "890277277",
    "price": "",
    "zipCode": "98042",
    "type": "SingleFamilyHome",
    "beds": "4.0",
    "baths": "1.0",
    "squareFeet": "1580.0",
    "imageUrl": "https://dal6rfqhhpk45.cloudfront.net/f066faf2224c3272f29dfe65b0b734c3357e5025_md2.jpg"
  },
  {
    "id": "890289948",
    "price": "",
    "zipCode": "98042",
    "type": "SingleFamilyHome",
    "beds": "3.0",
    "baths": "2.0",
    "squareFeet": "1780.0",
    "imageUrl": "https://dal6rfqhhpk45.cloudfront.net/793ee177ee0395414a774cf2d2883e1676d63afa_md2.jpg"
  },
  {
    "id": "890290194",
    "price": "",
    "zipCode": "98042",
    "type": "SingleFamilyHome",
    "beds": "4.0",
    "baths": "2.0",
    "squareFeet": "1961.0",
    "imageUrl": "https://dal6rfqhhpk45.cloudfront.net/d16a33ff1126f589688c3aeecd34ff43ecc6d920_md2.jpg"
  },
  {
    "id": "902333236",
    "price": "",
    "zipCode": "98030",
    "type": "SingleFamilyHome",
    "beds": "2.0",
    "baths": "1.0",
    "squareFeet": "930.0",
    "imageUrl": "https://dal6rfqhhpk45.cloudfront.net/033fe7cf592b27d86b25057068d765fdce3b2050_md2.jpg"
  },
  {
    "id": "906029258",
    "price": "",
    "zipCode": "98003",
    "type": "SingleFamilyHome",
    "beds": "2.0",
    "baths": "2.0",
    "squareFeet": "975.0",
    "imageUrl": "https://dal6rfqhhpk45.cloudfront.net/51d97f957f13d55fa4ddadbc993c9506e1aa2372_md2.jpg"
  },
  {
    "id": "890700502",
    "price": "",
    "zipCode": "866",
    "type": "98003",
    "beds": "2.0",
    "baths": "1.0",
    "squareFeet": "774.0",
    "imageUrl": "https://dal6rfqhhpk45.cloudfront.net/d6ce91a47296be2ffae13940daf1d9831279b99b_md2.jpg"
  },
  {
    "id": "890633924",
    "price": "",
    "zipCode": "98003",
    "type": "SingleFamilyHome",
    "beds": "3.0",
    "baths": "1.0",
    "squareFeet": "1020.0",
    "imageUrl": "https://dal6rfqhhpk45.cloudfront.net/b25ded7bd35a88cb162d33a66fa99a6b187d8039_md2.jpg"
  },
  {
    "id": "890606883",
    "price": "",
    "zipCode": "98032",
    "type": "SingleFamilyHome",
    "beds": "2.0",
    "baths": "2.0",
    "squareFeet": "1085.0",
    "imageUrl": "https://dal6rfqhhpk45.cloudfront.net/bc3c8a10813cff908265fab04f5ff5a6b6330866_md2.jpg"
  },
  {
    "id": "890664974",
    "price": "",
    "zipCode": "98003",
    "type": "SingleFamilyHome",
    "beds": "1.0",
    "baths": "1.0",
    "squareFeet": "450.0",
    "imageUrl": "https://dal6rfqhhpk45.cloudfront.net/cbf27932aaeb3eecbeef554a7ba8c22d14e4292c_md2.jpg"
  },
  {
    "id": "890588389",
    "price": "",
    "zipCode": "98030",
    "type": "SingleFamilyHome",
    "beds": "4.0",
    "baths": "2.0",
    "squareFeet": "2680.0",
    "imageUrl": "https://dal6rfqhhpk45.cloudfront.net/f6688c5ce2f03b4f0e947b48aae5989fbfef0ba2_md2.jpg"
  },
  {
    "id": "890690681",
    "price": "",
    "zipCode": "98001",
    "type": "SingleFamilyHome",
    "beds": "1.0",
    "baths": "1.0",
    "squareFeet": "850.0",
    "imageUrl": "https://dal6rfqhhpk45.cloudfront.net/e3208166564d26a95a985206d28bf57304a44419_md2.jpg"
  },
  {
    "id": "918476084",
    "price": "",
    "zipCode": "98002",
    "type": "SingleFamilyHome",
    "beds": "2.0",
    "baths": "1.0",
    "squareFeet": "1790.0",
    "imageUrl": "https://dal6rfqhhpk45.cloudfront.net/74dc0cc18f6eae50dcfbed7d8a6ec3a15242018d_md2.jpg"
  },
  {
    "id": "898375800",
    "price": "",
    "zipCode": "500",
    "type": "98002",
    "beds": "2.0",
    "baths": "1.0",
    "squareFeet": "1344.0",
    "imageUrl": "https://dal6rfqhhpk45.cloudfront.net/b10c28540f75197af6c2b220b93878ff3d4c9640_md2.jpg"
  },
  {
    "id": "900899427",
    "price": "",
    "zipCode": "98002",
    "type": "SingleFamilyHome",
    "beds": "2.0",
    "baths": "1.0",
    "squareFeet": "1090.0",
    "imageUrl": "https://dal6rfqhhpk45.cloudfront.net/6554bd0ae2963b65353ce0b7e952be684468d1d6_md2.jpg"
  },
  {
    "id": "889944922",
    "price": "",
    "zipCode": "98002",
    "type": "SingleFamilyHome",
    "beds": "2.0",
    "baths": "2.0",
    "squareFeet": "820.0",
    "imageUrl": "https://dal6rfqhhpk45.cloudfront.net/0350b9b085f4941fc0f3a555cad7962225b5b3c3_md2.jpg"
  },
  {
    "id": "883429906",
    "price": "",
    "zipCode": "0",
    "type": "98002",
    "beds": "3.0",
    "baths": "2.0",
    "squareFeet": "1330.0",
    "imageUrl": "https://dal6rfqhhpk45.cloudfront.net/a07207b62192cd85a7d6c698cf3bd380dc76e223_md2.jpg"
  },
  {
    "id": "876929465",
    "price": "",
    "zipCode": "98002",
    "type": "SingleFamilyHome",
    "beds": "5.0",
    "baths": "3.0",
    "squareFeet": "2300.0",
    "imageUrl": "https://dal6rfqhhpk45.cloudfront.net/0ddb1ee644b1880c02bbf853d764967268de4d14_md2.jpg"
  },
  {
    "id": "911967677",
    "price": "",
    "zipCode": "98002",
    "type": "SingleFamilyHome",
    "beds": "3.0",
    "baths": "2.0",
    "squareFeet": "1586.0",
    "imageUrl": "https://dal6rfqhhpk45.cloudfront.net/17d48ba696a49c891abfd1bece3c3631a99c6aed_md2.jpg"
  },
  {
    "id": "914243202",
    "price": "",
    "zipCode": "0",
    "type": "98002",
    "beds": "2.0",
    "baths": "1.0",
    "squareFeet": "910.0",
    "imageUrl": "https://dal6rfqhhpk45.cloudfront.net/870d51f9bbb42b62be057a1c495ec75c6d0a6685_md2.jpg"
  },
  {
    "id": "913116623",
    "price": "",
    "zipCode": "98002",
    "type": "SingleFamilyHome",
    "beds": "3.0",
    "baths": "1.0",
    "squareFeet": "1220.0",
    "imageUrl": "https://dal6rfqhhpk45.cloudfront.net/80cb38d6e97729f3a7ad8fb3f6a818898529be80_md2.jpg"
  },
  {
    "id": "917039042",
    "price": "",
    "zipCode": "900",
    "type": "98002",
    "beds": "3.0",
    "baths": "1.0",
    "squareFeet": "1180.0",
    "imageUrl": "https://dal6rfqhhpk45.cloudfront.net/2a8cff7e34dcf99469a4b57f2b98432a297cbd1f_md2.jpg"
  },
  {
    "id": "890313776",
    "price": "",
    "zipCode": "98002",
    "type": "TownhouseorCondo",
    "beds": "",
    "baths": "2.0",
    "squareFeet": "1740.0",
    "imageUrl": "https://dal6rfqhhpk45.cloudfront.net/03275b6f609a685b3debf4f476ed332cf13f2306_md2.jpg"
  },
  {
    "id": "883429995",
    "price": "",
    "zipCode": "98002",
    "type": "SingleFamilyHome",
    "beds": "",
    "baths": "3.0",
    "squareFeet": "3334.0",
    "imageUrl": "https://dal6rfqhhpk45.cloudfront.net/42888e90fb9763bb1cb32e8809f2835263acb737_md2.jpg"
  },
  {
    "id": "913012489",
    "price": "",
    "zipCode": "98002",
    "type": "TownhouseorCondo",
    "beds": "2.0",
    "baths": "2.0",
    "squareFeet": "1100.0",
    "imageUrl": "https://dal6rfqhhpk45.cloudfront.net/e7486145fabfc1709874c501eb92296808fabf71_md2.jpg"
  },
  {
    "id": "890529596",
    "price": "",
    "zipCode": "98002",
    "type": "SingleFamilyHome",
    "beds": "",
    "baths": "",
    "squareFeet": "",
    "imageUrl": "https://dal6rfqhhpk45.cloudfront.net/d819fd180a22c0b3240441365bcde36d15713009_md2.jpg"
  },
  {
    "id": "791418535",
    "price": "",
    "zipCode": "98002",
    "type": "SingleFamilyHome",
    "beds": "3.0",
    "baths": "2.0",
    "squareFeet": "1850.0",
    "imageUrl": "https://dal6rfqhhpk45.cloudfront.net/ef1c57696bccdc436f8bf881dc400ed062fd3f20_md2.jpg"
  },
  {
    "id": "878537192",
    "price": "",
    "zipCode": "98002",
    "type": "SingleFamilyHome",
    "beds": "3.0",
    "baths": "2.0",
    "squareFeet": "1202.0",
    "imageUrl": "https://dal6rfqhhpk45.cloudfront.net/79ede0d81df58c578b72269b81da118ffb5b8cad_md2.jpg"
  },
  {
    "id": "913725546",
    "price": "",
    "zipCode": "98002",
    "type": "SingleFamilyHome",
    "beds": "3.0",
    "baths": "2.0",
    "squareFeet": "1600.0",
    "imageUrl": "https://dal6rfqhhpk45.cloudfront.net/d8cfcac36e8e41c2fc8d23ebc77c88fbda29da45_md2.jpg"
  },
  {
    "id": "896454737",
    "price": "",
    "zipCode": "98002",
    "type": "SingleFamilyHome",
    "beds": "3.0",
    "baths": "2.0",
    "squareFeet": "1520.0",
    "imageUrl": "https://dal6rfqhhpk45.cloudfront.net/b4a8b7330749128f81d09090576ac7db407518a2_md2.jpg"
  },
  {
    "id": "912031862",
    "price": "",
    "zipCode": "0",
    "type": "98002",
    "beds": "1.0",
    "baths": "1.0",
    "squareFeet": "609.0",
    "imageUrl": "https://dal6rfqhhpk45.cloudfront.net/119b9c0f65616e75b18d05f5b42c797124819e9d_md2.jpg"
  },
  {
    "id": "908897559",
    "price": "",
    "zipCode": "98002",
    "type": "TownhouseorCondo",
    "beds": "6.0",
    "baths": "4.0",
    "squareFeet": "3960.0",
    "imageUrl": "https://dal6rfqhhpk45.cloudfront.net/9e7c27756846deae741021c2253c1b342e57f2f0_md2.jpg"
  },
  {
    "id": "907286888",
    "price": "",
    "zipCode": "98002",
    "type": "SingleFamilyHome",
    "beds": "3.0",
    "baths": "2.0",
    "squareFeet": "1840.0",
    "imageUrl": "https://dal6rfqhhpk45.cloudfront.net/7584b73b87fb6b5c18c3ca1cb46215ceb96f0e59_md2.jpg"
  },
  {
    "id": "877025865",
    "price": "",
    "zipCode": "0",
    "type": "98002",
    "beds": "2.0",
    "baths": "1.0",
    "squareFeet": "920.0",
    "imageUrl": "https://dal6rfqhhpk45.cloudfront.net/c04dcccf474e951bd791d0d0e8ce3a25712d4422_md2.jpg"
  },
  {
    "id": "889004706",
    "price": "",
    "zipCode": "98002",
    "type": "SingleFamilyHome",
    "beds": "",
    "baths": "",
    "squareFeet": "",
    "imageUrl": "https://dal6rfqhhpk45.cloudfront.net/4e8fe72abcbee7f491afc82a08c45d5ca98e8657_md2.jpg"
  },
  {
    "id": "907063383",
    "price": "",
    "zipCode": "98002",
    "type": "SingleFamilyHome",
    "beds": "3.0",
    "baths": "2.0",
    "squareFeet": "2520.0",
    "imageUrl": "https://dal6rfqhhpk45.cloudfront.net/85c4446661c607878dc2cb40c196f0388315835a_md2.jpg"
  },
  {
    "id": "889291382",
    "price": "",
    "zipCode": "0",
    "type": "98002",
    "beds": "3.0",
    "baths": "2.0",
    "squareFeet": "1125.0",
    "imageUrl": "https://dal6rfqhhpk45.cloudfront.net/5d6f4cd5d0b4bc1398be9f638c4e87410a6b2e07_md2.jpg"
  },
  {
    "id": "911529426",
    "price": "",
    "zipCode": "98001",
    "type": "TownhouseorCondo",
    "beds": "",
    "baths": "",
    "squareFeet": "3900.0",
    "imageUrl": "https://dal6rfqhhpk45.cloudfront.net/dfb44aedd87cdc6b99953e40b1141ed1a3b47fef_md2.jpg"
  },
  {
    "id": "919057981",
    "price": "",
    "zipCode": "98092",
    "type": "SingleFamilyHome",
    "beds": "2.0",
    "baths": "1.0",
    "squareFeet": "860.0",
    "imageUrl": "https://dal6rfqhhpk45.cloudfront.net/67a6a143688a619cda248f7fc40ada7e999db431_md2.jpg"
  },
  {
    "id": "904598507",
    "price": "",
    "zipCode": "98002",
    "type": "SingleFamilyHome",
    "beds": "3.0",
    "baths": "2.0",
    "squareFeet": "2670.0",
    "imageUrl": "https://dal6rfqhhpk45.cloudfront.net/dbb1b12268f22245df1fbb38204548b8234026b1_md2.jpg"
  },
  {
    "id": "900454001",
    "price": "",
    "zipCode": "98002",
    "type": "TownhouseorCondo",
    "beds": "3.0",
    "baths": "1.0",
    "squareFeet": "2220.0",
    "imageUrl": "https://dal6rfqhhpk45.cloudfront.net/a4eb5fb19208eb00d135421d04e5c36aa1aa4531_md2.jpg"
  },
  {
    "id": "919791091",
    "price": "",
    "zipCode": "98002",
    "type": "TownhouseorCondo",
    "beds": "",
    "baths": "",
    "squareFeet": "6849.0",
    "imageUrl": "https://dal6rfqhhpk45.cloudfront.net/c9d73622e013ce3e011228a7a870535569b638af_md2.jpg"
  },
  {
    "id": "890966256",
    "price": "",
    "zipCode": "98001",
    "type": "TownhouseorCondo",
    "beds": "",
    "baths": "",
    "squareFeet": "1572.0",
    "imageUrl": "https://dal6rfqhhpk45.cloudfront.net/b5791f819377ad774c2fb696ab1177b32500c9b0_md2.jpg"
  },
  {
    "id": "910902074",
    "price": "",
    "zipCode": "98002",
    "type": "SingleFamilyHome",
    "beds": "3.0",
    "baths": "2.0",
    "squareFeet": "2130.0",
    "imageUrl": "https://dal6rfqhhpk45.cloudfront.net/014680c934c16b08d9faf09a209cf4f32236b962_md2.jpg"
  },
  {
    "id": "891166727",
    "price": "",
    "zipCode": "0",
    "type": "98002",
    "beds": "2.0",
    "baths": "2.0",
    "squareFeet": "1082.0",
    "imageUrl": "https://dal6rfqhhpk45.cloudfront.net/4f9bede4cd768a70de70ea0d74e1a45b99345be5_md2.jpg"
  },
  {
    "id": "888013615",
    "price": "",
    "zipCode": "98092",
    "type": "SingleFamilyHome",
    "beds": "3.0",
    "baths": "1.0",
    "squareFeet": "2770.0",
    "imageUrl": "https://dal6rfqhhpk45.cloudfront.net/e22188514a1308524bba0b1dbdbfcc3828be0adb_md2.jpg"
  },
  {
    "id": "890685616",
    "price": "",
    "zipCode": "98092",
    "type": "SingleFamilyHome",
    "beds": "",
    "baths": "",
    "squareFeet": "",
    "imageUrl": "https://dal6rfqhhpk45.cloudfront.net/e189d365bcc6937987f0facda1c590d195d78c30_md2.jpg"
  },
  {
    "id": "920332232",
    "price": "",
    "zipCode": "0",
    "type": "98092",
    "beds": "2.0",
    "baths": "2.0",
    "squareFeet": "1160.0",
    "imageUrl": "https://dal6rfqhhpk45.cloudfront.net/2573a68963b6535ac78b8ad2f8cc1bb23cd7e3a2_md2.jpg"
  },
  {
    "id": "912719154",
    "price": "",
    "zipCode": "0",
    "type": "98092",
    "beds": "3.0",
    "baths": "2.0",
    "squareFeet": "1365.0",
    "imageUrl": "https://dal6rfqhhpk45.cloudfront.net/36db887527815324b65a9235263c73687012c45e_md2.jpg"
  },
  {
    "id": "890682728",
    "price": "",
    "zipCode": "500",
    "type": "98092",
    "beds": "2.0",
    "baths": "2.0",
    "squareFeet": "1213.0",
    "imageUrl": "https://dal6rfqhhpk45.cloudfront.net/1105388e3e32c32e5daa0d0e664d3cc8a23febd5_md2.jpg"
  },
  {
    "id": "890682727",
    "price": "",
    "zipCode": "950",
    "type": "98092",
    "beds": "3.0",
    "baths": "2.0",
    "squareFeet": "1414.0",
    "imageUrl": "https://dal6rfqhhpk45.cloudfront.net/07abad9515739aec9cd3de93f9bf025980e7c197_md2.jpg"
  },
  {
    "id": "912719153",
    "price": "",
    "zipCode": "0",
    "type": "98092",
    "beds": "2.0",
    "baths": "1.0",
    "squareFeet": "1160.0",
    "imageUrl": "https://dal6rfqhhpk45.cloudfront.net/6d924126c436d0ae27dd0327fb80e8818357dbd4_md2.jpg"
  },
  {
    "id": "912737473",
    "price": "",
    "zipCode": "98092",
    "type": "SingleFamilyHome",
    "beds": "4.0",
    "baths": "3.0",
    "squareFeet": "3436.0",
    "imageUrl": "https://dal6rfqhhpk45.cloudfront.net/d99594bcc6153c70c2e84dc0d5f26de4aa427605_md2.jpg"
  },
  {
    "id": "901361062",
    "price": "",
    "zipCode": "98002",
    "type": "TownhouseorCondo",
    "beds": "6.0",
    "baths": "3.0",
    "squareFeet": "2290.0",
    "imageUrl": "https://dal6rfqhhpk45.cloudfront.net/0c1cfad7d45aa356576519ef530fac6659d30a37_md2.jpg"
  },
  {
    "id": "890427743",
    "price": "",
    "zipCode": "98002",
    "type": "SingleFamilyHome",
    "beds": "",
    "baths": "",
    "squareFeet": "2020.0",
    "imageUrl": "https://dal6rfqhhpk45.cloudfront.net/16dca5a8e061650462e78a54c7c5ea951a1b1691_md2.jpg"
  },
  {
    "id": "918496795",
    "price": "",
    "zipCode": "98092",
    "type": "SingleFamilyHome",
    "beds": "3.0",
    "baths": "2.0",
    "squareFeet": "2190.0",
    "imageUrl": "https://dal6rfqhhpk45.cloudfront.net/584e30c870fdde7da4ee36ebe518f962fec46051_md2.jpg"
  },
  {
    "id": "907407280",
    "price": "",
    "zipCode": "98002",
    "type": "SingleFamilyHome",
    "beds": "2.0",
    "baths": "2.0",
    "squareFeet": "1350.0",
    "imageUrl": "https://dal6rfqhhpk45.cloudfront.net/a102ea3d622e4967fd8946647fb1e4188c041088_md2.jpg"
  },
  {
    "id": "913203187",
    "price": "",
    "zipCode": "98002",
    "type": "SingleFamilyHome",
    "beds": "3.0",
    "baths": "1.0",
    "squareFeet": "960.0",
    "imageUrl": "https://dal6rfqhhpk45.cloudfront.net/53452b468f1b29c0b45a0f67ae390ee418ac5129_md2.jpg"
  },
  {
    "id": "890678472",
    "price": "",
    "zipCode": "950",
    "type": "98092",
    "beds": "3.0",
    "baths": "",
    "squareFeet": "1260.0",
    "imageUrl": "https://dal6rfqhhpk45.cloudfront.net/2ee901c5f5dfc0e51ebb6f473e08512bd036bad9_md2.jpg"
  },
  {
    "id": "890678470",
    "price": "",
    "zipCode": "0",
    "type": "98092",
    "beds": "3.0",
    "baths": "",
    "squareFeet": "1260.0",
    "imageUrl": "https://dal6rfqhhpk45.cloudfront.net/d86ce960fb4506008c45493bdf6e9b27d28b7230_md2.jpg"
  },
  {
    "id": "890678471",
    "price": "",
    "zipCode": "0",
    "type": "98092",
    "beds": "3.0",
    "baths": "",
    "squareFeet": "1260.0",
    "imageUrl": "https://dal6rfqhhpk45.cloudfront.net/cec8ae765680a0626ed3029c85de16cd8b3a684e_md2.jpg"
  },
  {
    "id": "890372334",
    "price": "",
    "zipCode": "98002",
    "type": "SingleFamilyHome",
    "beds": "4.0",
    "baths": "1.0",
    "squareFeet": "1200.0",
    "imageUrl": "https://dal6rfqhhpk45.cloudfront.net/27a9a096b0f97a903f02fc47d0840ed9ff09e523_md2.jpg"
  },
  {
    "id": "883041548",
    "price": "",
    "zipCode": "0",
    "type": "98001",
    "beds": "2.0",
    "baths": "1.0",
    "squareFeet": "1110.0",
    "imageUrl": "https://dal6rfqhhpk45.cloudfront.net/ebf3dbb872d2c2d2b3c32e4440cd7a7a19fed861_md2.jpg"
  },
  {
    "id": "920326899",
    "price": "",
    "zipCode": "0",
    "type": "98092",
    "beds": "2.0",
    "baths": "1.0",
    "squareFeet": "1260.0",
    "imageUrl": "https://dal6rfqhhpk45.cloudfront.net/8277c4b27fe5483c5c9a4fa9d1cb29b1f8a8ba51_md2.jpg"
  },
  {
    "id": "917883661",
    "price": "",
    "zipCode": "98092",
    "type": "SingleFamilyHome",
    "beds": "4.0",
    "baths": "2.0",
    "squareFeet": "2090.0",
    "imageUrl": "https://dal6rfqhhpk45.cloudfront.net/d1da6858cca50c1af5a3c9f9bb23fea3fc2166e8_md2.jpg"
  },
  {
    "id": "919052526",
    "price": "",
    "zipCode": "950",
    "type": "98092",
    "beds": "2.0",
    "baths": "1.0",
    "squareFeet": "1260.0",
    "imageUrl": "https://dal6rfqhhpk45.cloudfront.net/f00f4bf52fa17b88ef8af32399eb3b8c00d1d7db_md2.jpg"
  },
  {
    "id": "901561414",
    "price": "",
    "zipCode": "0",
    "type": "98092",
    "beds": "2.0",
    "baths": "1.0",
    "squareFeet": "1280.0",
    "imageUrl": "https://dal6rfqhhpk45.cloudfront.net/6bb08a92aba3615cd3934007f7cdce5de6be3d75_md2.jpg"
  },
  {
    "id": "901561413",
    "price": "",
    "zipCode": "0",
    "type": "98092",
    "beds": "2.0",
    "baths": "1.0",
    "squareFeet": "1280.0",
    "imageUrl": "https://dal6rfqhhpk45.cloudfront.net/9ba0c58ebf238a6fdb21107740ac7c4183099efd_md2.jpg"
  },
  {
    "id": "886352853",
    "price": "",
    "zipCode": "0",
    "type": "98092",
    "beds": "2.0",
    "baths": "1.0",
    "squareFeet": "1260.0",
    "imageUrl": "https://dal6rfqhhpk45.cloudfront.net/8704e5f9ec7cecf09a5296bb21bd943b9141251d_md2.jpg"
  },
  {
    "id": "886352851",
    "price": "",
    "zipCode": "0",
    "type": "98092",
    "beds": "2.0",
    "baths": "2.0",
    "squareFeet": "1768.0",
    "imageUrl": "https://dal6rfqhhpk45.cloudfront.net/8b3f59ba5392ee6353938e2cf7d3717e87fe2c99_md2.jpg"
  },
  {
    "id": "890676929",
    "price": "",
    "zipCode": "0",
    "type": "98092",
    "beds": "2.0",
    "baths": "2.0",
    "squareFeet": "1215.0",
    "imageUrl": "https://dal6rfqhhpk45.cloudfront.net/90408e624bbd10cfc269e22d3b7e7843256d6184_md2.jpg"
  },
  {
    "id": "890540485",
    "price": "",
    "zipCode": "0",
    "type": "98002",
    "beds": "3.0",
    "baths": "2.0",
    "squareFeet": "1344.0",
    "imageUrl": "https://dal6rfqhhpk45.cloudfront.net/ea165c59ccff37f8091e6b1196b8de9b8e31e7ad_md2.jpg"
  },
  {
    "id": "890445498",
    "price": "",
    "zipCode": "950",
    "type": "98002",
    "beds": "2.0",
    "baths": "2.0",
    "squareFeet": "1140.0",
    "imageUrl": "https://dal6rfqhhpk45.cloudfront.net/7065ac301909b17dfe71784d08101c3e1f732c04_md2.jpg"
  },
  {
    "id": "916257880",
    "price": "",
    "zipCode": "98092",
    "type": "SingleFamilyHome",
    "beds": "3.0",
    "baths": "1.0",
    "squareFeet": "1520.0",
    "imageUrl": "https://dal6rfqhhpk45.cloudfront.net/5bf1ea7387dfc57a78fe6f28ac1c4c030ddb38e0_md2.jpg"
  },
  {
    "id": "913390361",
    "price": "",
    "zipCode": "98002",
    "type": "SingleFamilyHome",
    "beds": "3.0",
    "baths": "1.0",
    "squareFeet": "1590.0",
    "imageUrl": "https://dal6rfqhhpk45.cloudfront.net/642dbb70dc3b7a0a42af6cba5dc54df78c13e49a_md2.jpg"
  },
  {
    "id": "880906415",
    "price": "",
    "zipCode": "98092",
    "type": "SingleFamilyHome",
    "beds": "4.0",
    "baths": "2.0",
    "squareFeet": "2030.0",
    "imageUrl": "https://dal6rfqhhpk45.cloudfront.net/a18a7a40477bfb503e5066392695fd345bad809a_md2.jpg"
  },
  {
    "id": "888043365",
    "price": "",
    "zipCode": "98092",
    "type": "SingleFamilyHome",
    "beds": "3.0",
    "baths": "2.0",
    "squareFeet": "1390.0",
    "imageUrl": "https://dal6rfqhhpk45.cloudfront.net/1fec4a65da1f747c94f98277559cd6fa20f5e99a_md2.jpg"
  },
  {
    "id": "896023297",
    "price": "",
    "zipCode": "98092",
    "type": "SingleFamilyHome",
    "beds": "4.0",
    "baths": "2.0",
    "squareFeet": "2900.0",
    "imageUrl": "https://dal6rfqhhpk45.cloudfront.net/a115de07beedb556788882b6dee42b04b9489f81_md2.jpg"
  },
  {
    "id": "890303412",
    "price": "",
    "zipCode": "900",
    "type": "98002",
    "beds": "3.0",
    "baths": "",
    "squareFeet": "1600.0",
    "imageUrl": "https://dal6rfqhhpk45.cloudfront.net/486b61c40e6af8dbbfd7ba80480a0aa3d31f7aa7_md2.jpg"
  },
  {
    "id": "890303411",
    "price": "",
    "zipCode": "0",
    "type": "98002",
    "beds": "3.0",
    "baths": "",
    "squareFeet": "1874.0",
    "imageUrl": "https://dal6rfqhhpk45.cloudfront.net/d2b80ce593a78a30397ae9c8942be040565f3f2d_md2.jpg"
  },
  {
    "id": "890303407",
    "price": "",
    "zipCode": "950",
    "type": "98002",
    "beds": "2.0",
    "baths": "",
    "squareFeet": "1560.0",
    "imageUrl": "https://dal6rfqhhpk45.cloudfront.net/a6e983334153c651ef1d6bd03101a7e4c6bfcac8_md2.jpg"
  },
  {
    "id": "914715243",
    "price": "",
    "zipCode": "98092",
    "type": "SingleFamilyHome",
    "beds": "4.0",
    "baths": "2.0",
    "squareFeet": "2350.0",
    "imageUrl": "https://dal6rfqhhpk45.cloudfront.net/9a7510f621f966ce7bd21bda853e089918013e90_md2.jpg"
  },
  {
    "id": "890675335",
    "price": "",
    "zipCode": "0",
    "type": "98092",
    "beds": "2.0",
    "baths": "2.0",
    "squareFeet": "1215.0",
    "imageUrl": "https://dal6rfqhhpk45.cloudfront.net/53ca22fd8cf15bbcbc606aef9be13dee792b6c7b_md2.jpg"
  },
  {
    "id": "920045694",
    "price": "",
    "zipCode": "98002",
    "type": "SingleFamilyHome",
    "beds": "3.0",
    "baths": "1.0",
    "squareFeet": "1430.0",
    "imageUrl": "https://dal6rfqhhpk45.cloudfront.net/ab1a7a617d163a1dae836bb1f37255674e98d3f3_md2.jpg"
  },
  {
    "id": "887387858",
    "price": "",
    "zipCode": "98092",
    "type": "SingleFamilyHome",
    "beds": "5.0",
    "baths": "2.0",
    "squareFeet": "2910.0",
    "imageUrl": "https://dal6rfqhhpk45.cloudfront.net/651152d93212d06c7ae9462a1538afb3c38a8b97_md2.jpg"
  }
]